endpoints/__init__.py
endpoints/endpoint.py
playground_resumeparser-0.0.1.dist-info/METADATA
playground_resumeparser-0.0.1.dist-info/RECORD
playground_resumeparser-0.0.1.dist-info/WHEEL
playground_resumeparser-0.0.1.dist-info/entry_points.txt
playground_resumeparser-0.0.1.dist-info/top_level.txt
resumeparser/__init__.py
resumeparser/resume_parser.py
util/__init__.py
util/data_converter.py
